Metadata-Version: 2.1
Name: pairk
Version: 1.0.7
Summary: motif conservation in IDRs through pairwise k-mer alignment
Author-email: Jackson Halpin <jhalpin@mit.edu>
License: MIT
Project-URL: Source, https://github.com/jacksonh1/pairk/
Project-URL: Documentation, https://pairk.readthedocs.io/
Classifier: License :: OSI Approved :: MIT License
Classifier: Programming Language :: Python :: 3
Requires-Python: >=3.10
License-File: LICENSE
Requires-Dist: importlib-resources
Requires-Dist: numpy
Requires-Dist: pandas
Requires-Dist: torch
Requires-Dist: torchvision
Requires-Dist: biopython >=1.8
Requires-Dist: fair-esm
Requires-Dist: transformers
Requires-Dist: alfpy
Requires-Dist: logomaker
Requires-Dist: matplotlib
Requires-Dist: seaborn
Provides-Extra: test
Requires-Dist: pytest >=6.1.2 ; extra == 'test'
